finanzonline_databox/__init__.py
finanzonline_databox/__init__conf__.py
finanzonline_databox/__main__.py
finanzonline_databox/_datetime_utils.py
finanzonline_databox/_format_utils.py
finanzonline_databox/behaviors.py
finanzonline_databox/cli.py
finanzonline_databox/config.py
finanzonline_databox/config_deploy.py
finanzonline_databox/config_schema.py
finanzonline_databox/config_show.py
finanzonline_databox/defaultconfig.toml
finanzonline_databox/enums.py
finanzonline_databox/i18n.py
finanzonline_databox/logging_setup.py
finanzonline_databox/mail.py
finanzonline_databox/py.typed
finanzonline_databox/adapters/__init__.py
finanzonline_databox/adapters/finanzonline/__init__.py
finanzonline_databox/adapters/finanzonline/databox_client.py
finanzonline_databox/adapters/finanzonline/session_client.py
finanzonline_databox/adapters/notification/__init__.py
finanzonline_databox/adapters/notification/email_adapter.py
finanzonline_databox/adapters/output/__init__.py
finanzonline_databox/adapters/output/formatters.py
finanzonline_databox/application/__init__.py
finanzonline_databox/application/ports.py
finanzonline_databox/application/use_cases.py
finanzonline_databox/defaultconfig.d/20-email.toml
finanzonline_databox/defaultconfig.d/30-logging.toml
finanzonline_databox/domain/__init__.py
finanzonline_databox/domain/errors.py
finanzonline_databox/domain/models.py
finanzonline_databox/domain/return_codes.py
finanzonline_databox/locales/messages.pot
finanzonline_databox/locales/de/LC_MESSAGES/messages.mo
finanzonline_databox/locales/de/LC_MESSAGES/messages.po
finanzonline_databox/locales/es/LC_MESSAGES/messages.mo
finanzonline_databox/locales/es/LC_MESSAGES/messages.po
finanzonline_databox/locales/fr/LC_MESSAGES/messages.mo
finanzonline_databox/locales/fr/LC_MESSAGES/messages.po
finanzonline_databox/locales/ru/LC_MESSAGES/messages.mo
finanzonline_databox/locales/ru/LC_MESSAGES/messages.po
finanzonline_databox-1.2.12.dist-info/METADATA
finanzonline_databox-1.2.12.dist-info/WHEEL
finanzonline_databox-1.2.12.dist-info/entry_points.txt
finanzonline_databox-1.2.12.dist-info/licenses/LICENSE
finanzonline_databox-1.2.12.dist-info/RECORD
