Metadata-Version: 2.4
Name: finanzonline_databox
Version: 1.2.12
Summary: Python library and CLI for downloading documents from FinanzOnline Austria DataBox
Project-URL: Homepage, https://github.com/bitranox/finanzonline_databox
Project-URL: Repository, https://github.com/bitranox/finanzonline_databox.git
Project-URL: Issues, https://github.com/bitranox/finanzonline_databox/issues
Author-email: bitranox <bitranox@gmail.com>
License: MIT
License-File: LICENSE
Keywords: austria,cli,databox,documents,download,finanzonline,tax
Classifier: Environment :: Console
Classifier: License :: OSI Approved :: MIT License
Classifier: Operating System :: OS Independent
Classifier: Programming Language :: Python :: 3
Classifier: Programming Language :: Python :: 3 :: Only
Classifier: Programming Language :: Python :: 3.10
Classifier: Programming Language :: Python :: 3.11
Classifier: Programming Language :: Python :: 3.12
Classifier: Programming Language :: Python :: 3.13
Classifier: Typing :: Typed
Requires-Python: >=3.10
Requires-Dist: btx-lib-mail>=1.3.0
Requires-Dist: filelock>=3.20.3
Requires-Dist: lib-cli-exit-tools>=2.2.4
Requires-Dist: lib-layered-config>=5.4.0
Requires-Dist: lib-log-rich>=6.3.1
Requires-Dist: orjson>=3.11.6
Requires-Dist: rich-click>=1.9.7
Requires-Dist: zeep>=4.3.2
Provides-Extra: dev
Requires-Dist: bandit>=1.9.3; extra == 'dev'
Requires-Dist: build>=1.4.0; extra == 'dev'
Requires-Dist: codecov-cli>=11.2.6; extra == 'dev'
Requires-Dist: import-linter>=2.9; extra == 'dev'
Requires-Dist: pip-audit>=2.10.0; extra == 'dev'
Requires-Dist: pyright[nodejs]>=1.1.408; extra == 'dev'
Requires-Dist: pytest-cov>=7.0.0; extra == 'dev'
Requires-Dist: pytest>=9.0.2; extra == 'dev'
Requires-Dist: rtoml>=0.13.0; extra == 'dev'
Requires-Dist: ruff>=0.14.14; extra == 'dev'
Requires-Dist: textual>=7.5.0; extra == 'dev'
Requires-Dist: twine>=6.2.0; extra == 'dev'
